odoo/addons/stock_location_address/README.rst
odoo/addons/stock_location_address/__init__.py
odoo/addons/stock_location_address/__manifest__.py
odoo/addons/stock_location_address/models/__init__.py
odoo/addons/stock_location_address/models/stock_location.py
odoo/addons/stock_location_address/static/description/icon.png
odoo/addons/stock_location_address/tests/__init__.py
odoo/addons/stock_location_address/tests/test_location_address.py
odoo/addons/stock_location_address/views/stock_location_views.xml
odoo11_addon_stock_location_address-11.0.1.0.0.99.dev1.dist-info/DESCRIPTION.rst
odoo11_addon_stock_location_address-11.0.1.0.0.99.dev1.dist-info/METADATA
odoo11_addon_stock_location_address-11.0.1.0.0.99.dev1.dist-info/RECORD
odoo11_addon_stock_location_address-11.0.1.0.0.99.dev1.dist-info/WHEEL
odoo11_addon_stock_location_address-11.0.1.0.0.99.dev1.dist-info/metadata.json
odoo11_addon_stock_location_address-11.0.1.0.0.99.dev1.dist-info/top_level.txt
